.DS_Store
rec_pangu/.DS_Store
rec_pangu/__init__.py
rec_pangu/benchmark_trainer.py
rec_pangu/gpt_ranktrainer.py
rec_pangu/model_pipeline.py
rec_pangu/old_ranktrainer.py
rec_pangu/trainer.py
rec_pangu/dataset/__init__.py
rec_pangu/dataset/base_dataset.py
rec_pangu/dataset/graph_dataset.py
rec_pangu/dataset/multi_task_dataset.py
rec_pangu/dataset/process_data.py
rec_pangu/dataset/sequence_dataset.py
rec_pangu/models/.DS_Store
rec_pangu/models/__init__.py
rec_pangu/models/base_model.py
rec_pangu/models/utils.py
rec_pangu/models/layers/LGConv.py
rec_pangu/models/layers/__init__.py
rec_pangu/models/layers/activation.py
rec_pangu/models/layers/attention.py
rec_pangu/models/layers/conv.py
rec_pangu/models/layers/deep.py
rec_pangu/models/layers/embedding.py
rec_pangu/models/layers/graph.py
rec_pangu/models/layers/interaction.py
rec_pangu/models/layers/multi_interest.py
rec_pangu/models/layers/sequence.py
rec_pangu/models/layers/shallow.py
rec_pangu/models/layers/trainformer.py
rec_pangu/models/multi_task/__init__.py
rec_pangu/models/multi_task/aitm.py
rec_pangu/models/multi_task/essm.py
rec_pangu/models/multi_task/mlmmoe.py
rec_pangu/models/multi_task/mmoe.py
rec_pangu/models/multi_task/omoe.py
rec_pangu/models/multi_task/sharebottom.py
rec_pangu/models/ranking/__init__.py
rec_pangu/models/ranking/afm.py
rec_pangu/models/ranking/afn.py
rec_pangu/models/ranking/aoanet.py
rec_pangu/models/ranking/autoint.py
rec_pangu/models/ranking/ccpm.py
rec_pangu/models/ranking/dcn.py
rec_pangu/models/ranking/deepfm.py
rec_pangu/models/ranking/fibinet.py
rec_pangu/models/ranking/fm.py
rec_pangu/models/ranking/lightgcn.py
rec_pangu/models/ranking/lr.py
rec_pangu/models/ranking/masknet.py
rec_pangu/models/ranking/nfm.py
rec_pangu/models/ranking/wdl.py
rec_pangu/models/ranking/xdeepfm.py
rec_pangu/models/sequence/__init__.py
rec_pangu/models/sequence/clrec.py
rec_pangu/models/sequence/cmi.py
rec_pangu/models/sequence/comirec.py
rec_pangu/models/sequence/contrarec.py
rec_pangu-0.4.1.dist-info/LICENSE
rec_pangu-0.4.1.dist-info/METADATA
rec_pangu-0.4.1.dist-info/WHEEL
rec_pangu-0.4.1.dist-info/top_level.txt
rec_pangu-0.4.1.dist-info/RECORD
