Metadata-Version: 2.1
Name: rec-pangu
Version: 0.4.1
Summary: Some Rank/Multi-task model implemented by Pytorch
Home-page: https://github.com/HaSai666/rec_pangu
Author: wk
Author-email: 306178200@qq.com
Keywords: rank,multi task,deep learning,pytorch,recsys,recommendation
Platform: all
Classifier: Intended Audience :: Developers
Classifier: Intended Audience :: Education
Classifier: Intended Audience :: Science/Research
Classifier: Operating System :: OS Independent
Classifier: Programming Language :: Python :: 3
Classifier: Programming Language :: Python :: 3.7
Classifier: Programming Language :: Python :: 3.8
Classifier: Programming Language :: Python :: 3.9
Classifier: Topic :: Scientific/Engineering
Classifier: Topic :: Scientific/Engineering :: Artificial Intelligence
Classifier: Topic :: Software Development :: Libraries
Classifier: Topic :: Software Development :: Libraries :: Python Modules
Classifier: License :: OSI Approved :: MIT License
License-File: LICENSE
Requires-Dist: numpy (>=1.19.0)
Requires-Dist: torch (>=1.7.0)
Requires-Dist: pandas (==1.3.5)
Requires-Dist: tqdm
Requires-Dist: scikit-learn (>=0.23.2)
Requires-Dist: pygments
Requires-Dist: loguru
Requires-Dist: faiss-cpu
Requires-Dist: wandb
